dawg_python/__init__.py
dawg_python/compat.py
dawg_python/dawgs.py
dawg_python/units.py
dawg_python/wrapper.py
DAWG_Python-0.7.2.dist-info/DESCRIPTION.rst
DAWG_Python-0.7.2.dist-info/METADATA
DAWG_Python-0.7.2.dist-info/metadata.json
DAWG_Python-0.7.2.dist-info/RECORD
DAWG_Python-0.7.2.dist-info/top_level.txt
DAWG_Python-0.7.2.dist-info/WHEEL
